pyserverchan/__init__.py
pyserverchan/pyserver.py
pyserverchan-0.0.4.dist-info/LICENSE
pyserverchan-0.0.4.dist-info/METADATA
pyserverchan-0.0.4.dist-info/WHEEL
pyserverchan-0.0.4.dist-info/top_level.txt
pyserverchan-0.0.4.dist-info/RECORD
