Metadata-Version: 2.1
Name: pyserverchan
Version: 0.0.4
Summary: Server-chan for python.
Home-page: https://github.com/GanjinZero/pyserverchan
Author: GanjinZero
Author-email: yuanz17@mails.tsinghua.edu.cn
License: UNKNOWN
Platform: UNKNOWN
Classifier: Programming Language :: Python :: 3
Classifier: License :: OSI Approved :: MIT License
Classifier: Operating System :: OS Independent
